{"_type":"export","__export_format":4,"__export_date":"2023-06-01T23:36:47.754Z","__export_source":"insomnia.desktop.app:v2022.4.2","resources":[{"_id":"req_46b095d20aa9482faabd4a01fcf9fa09","parentId":"fld_2af1945e824d4c58a7e2d303a0954ce0","modified":1685660196870,"created":1685660178732,"url":"http://localhost:3000/movies/1/comments","name":"Comments","description":"","method":"GET","body":{},"parameters":[],"headers":[],"authentication":{},"metaSortKey":-1685660178732,"isPrivate":false,"settingStoreCookies":true,"settingSendCookies":true,"settingDisableRenderRequestBody":false,"settingEncodeUrl":true,"settingRebuildPath":true,"settingFollowRedirects":"global","_type":"request"},{"_id":"fld_2af1945e824d4c58a7e2d303a0954ce0","parentId":"fld_0f0a0c06960a4fd78264547449265e5e","modified":1685660177445,"created":1685660175406,"name":"Comments","description":"","environment":{},"environmentPropertyOrder":null,"metaSortKey":-1685659978804,"_type":"request_group"},{"_id":"fld_0f0a0c06960a4fd78264547449265e5e","parentId":"wrk_386ec38631214ec28d12bb3f11e6841c","modified":1685659977072,"created":1685659977072,"name":"Movies","description":"","environment":{},"environmentPropertyOrder":null,"metaSortKey":-1685659977072,"_type":"request_group"},{"_id":"wrk_386ec38631214ec28d12bb3f11e6841c","parentId":null,"modified":1685659965917,"created":1685659965917,"name":"CinemApp","description":"","scope":"collection","_type":"workspace"},{"_id":"req_e663edd189614999ac10011e060bd9e1","parentId":"fld_2af1945e824d4c58a7e2d303a0954ce0","modified":1685660463709,"created":1685660233383,"url":"http://localhost:3000/movies/1/comments","name":"Create Comment","description":"","method":"POST","body":{"mimeType":"application/json","text":"{\n  \"userId\": 1,\n  \"movieId\": 1,\n  \"title\": \"No es una gran pelicula\",\n  \"body\": \"La verdad es que es una pelicula muy aburrida y se hace muy larga, en especial el final es bastante malo\",\n  \"rating\": 2\n}"},"parameters":[],"headers":[{"name":"Content-Type","value":"application/json","id":"pair_5e258c0d919f4d348110fcb335b81166"}],"authentication":{},"metaSortKey":-1685660078743,"isPrivate":false,"settingStoreCookies":true,"settingSendCookies":true,"settingDisableRenderRequestBody":false,"settingEncodeUrl":true,"settingRebuildPath":true,"settingFollowRedirects":"global","_type":"request"},{"_id":"req_4a184af1a0024bd3b0bfb8ec7820e4f0","parentId":"fld_0f0a0c06960a4fd78264547449265e5e","modified":1685660120008,"created":1685659978753,"url":"http://localhost:3000/movies","name":"Movies","description":"","method":"GET","body":{},"parameters":[],"headers":[],"authentication":{},"metaSortKey":-1685659978754,"isPrivate":false,"settingStoreCookies":true,"settingSendCookies":true,"settingDisableRenderRequestBody":false,"settingEncodeUrl":true,"settingRebuildPath":true,"settingFollowRedirects":"global","_type":"request"},{"_id":"req_91e796e894534025907fc517cd38abe6","parentId":"fld_0f0a0c06960a4fd78264547449265e5e","modified":1685660140442,"created":1685660137529,"url":"http://localhost:3000/movies/1","name":"Movie by id","description":"","method":"GET","body":{},"parameters":[],"headers":[],"authentication":{},"metaSortKey":-1670974425004.5,"isPrivate":false,"settingStoreCookies":true,"settingSendCookies":true,"settingDisableRenderRequestBody":false,"settingEncodeUrl":true,"settingRebuildPath":true,"settingFollowRedirects":"global","_type":"request"},{"_id":"env_cf2ed830b4927279503bd3f792884f5b50724d8e","parentId":"wrk_386ec38631214ec28d12bb3f11e6841c","modified":1685659965935,"created":1685659965935,"name":"Base Environment","data":{},"dataPropertyOrder":null,"color":null,"isPrivate":false,"metaSortKey":1685659965935,"_type":"environment"},{"_id":"jar_cf2ed830b4927279503bd3f792884f5b50724d8e","parentId":"wrk_386ec38631214ec28d12bb3f11e6841c","modified":1685659965938,"created":1685659965938,"name":"Default Jar","cookies":[],"_type":"cookie_jar"},{"_id":"spc_b9da049c285346479c579ebd014559ff","parentId":"wrk_386ec38631214ec28d12bb3f11e6841c","modified":1685659965922,"created":1685659965922,"fileName":"CinemApp","contents":"","contentType":"yaml","_type":"api_spec"}]}